pp_terminal/__init__.py
pp_terminal/commands/__init__.py
pp_terminal/commands/export_anonymized.py
pp_terminal/commands/simulate_interest.py
pp_terminal/commands/simulate_share_sell.py
pp_terminal/commands/simulate_vorabpauschale.py
pp_terminal/commands/validate.py
pp_terminal/commands/view_accounts.py
pp_terminal/commands/view_securities.py
pp_terminal/config.schema.json
pp_terminal/data/__init__.py
pp_terminal/data/attribute_type_converter.py
pp_terminal/data/filters.py
pp_terminal/data/pp_portfolio_builder.py
pp_terminal/data/ppxml2db_wrapper.py
pp_terminal/data/xml_anonymizer.py
pp_terminal/domain/__init__.py
pp_terminal/domain/portfolio.py
pp_terminal/domain/portfolio_snapshot.py
pp_terminal/domain/schemas.py
pp_terminal/exceptions.py
pp_terminal/main.py
pp_terminal/output/__init__.py
pp_terminal/output/column_utils.py
pp_terminal/output/strategy.py
pp_terminal/output/table_decorator.py
pp_terminal/utils/__init__.py
pp_terminal/utils/cache.py
pp_terminal/utils/config.py
pp_terminal/utils/helper.py
pp_terminal/utils/options.py
pp_terminal/utils/plugins.py
pp_terminal/validation/__init__.py
pp_terminal/validation/engine.py
pp_terminal/validation/rules.py
ppxml2db/.git
ppxml2db/LICENSE
ppxml2db/Makefile
ppxml2db/README.md
ppxml2db/account.sql
ppxml2db/account_attr.sql
ppxml2db/attribute_type.sql
ppxml2db/bookmark.sql
ppxml2db/config_entry.sql
ppxml2db/config_set.sql
ppxml2db/dashboard.sql
ppxml2db/db2ppxml.py
ppxml2db/dbhelper.py
ppxml2db/latest_price.sql
ppxml2db/ppxml2db.py
ppxml2db/ppxml2db.py.orig
ppxml2db/ppxml2db_init.py
ppxml2db/price.sql
ppxml2db/property.sql
ppxml2db/security.sql
ppxml2db/security_attr.sql
ppxml2db/security_event.sql
ppxml2db/security_prop.sql
ppxml2db/taxonomy.sql
ppxml2db/taxonomy_assignment.sql
ppxml2db/taxonomy_assignment_data.sql
ppxml2db/taxonomy_category.sql
ppxml2db/taxonomy_data.sql
ppxml2db/version.py
ppxml2db/watchlist.sql
ppxml2db/watchlist_security.sql
ppxml2db/xact.sql
ppxml2db/xact_cross_entry.sql
ppxml2db/xact_unit.sql
pp_terminal-0.7.0.dist-info/METADATA
pp_terminal-0.7.0.dist-info/WHEEL
pp_terminal-0.7.0.dist-info/entry_points.txt
pp_terminal-0.7.0.dist-info/licenses/LICENSE
pp_terminal-0.7.0.dist-info/RECORD
