Metadata-Version: 2.4
Name: pp-terminal
Version: 0.7.0
Summary: The Analytic Companion for Portfolio Performance
License-Expression: GPL-3.0-or-later
License-File: LICENSE
Author: Christoph Massmann
Author-email: chris@dev-investor.de
Requires-Python: >=3.13,<4.0.0
Classifier: Programming Language :: Python :: 3
Classifier: Programming Language :: Python :: 3.13
Classifier: Programming Language :: Python :: 3.14
Requires-Dist: babel (>=2.16.0,<3.0.0)
Requires-Dist: faker (>=33.1.0,<34.0.0)
Requires-Dist: jsonschema (>=4.23.0,<5.0.0)
Requires-Dist: lxml (>=5.3.0,<7.0.0)
Requires-Dist: pandas (>=2.2.3,<3.0.0)
Requires-Dist: pandera (>=0.28.0,<0.29.0)
Requires-Dist: rich (>=13.9.4,<15.0.0)
Requires-Dist: typer (>=0.15.1,<0.22.0)
Requires-Dist: typer-config (>=1.4.0,<2.0.0)
